rivector/__init__.py
rivector/errors.py
rivector/ext_library.cpython-312-darwin.so
rivector/vector2.py
rivector/wrapper.py
rivector-2023.1.17.1.dist-info/LICENSE
rivector-2023.1.17.1.dist-info/METADATA
rivector-2023.1.17.1.dist-info/WHEEL
rivector-2023.1.17.1.dist-info/top_level.txt
rivector-2023.1.17.1.dist-info/RECORD
