Metadata-Version: 2.1
Name: rivector
Version: 2023.1.17.1
Summary: Fast CPython library for Vectors
Author: risknu
Author-email: risknumail@gmail.com
Classifier: Programming Language :: Python :: 3
Classifier: License :: OSI Approved :: MIT License
Classifier: Operating System :: OS Independent
Requires-Python: >=3.11
License-File: LICENSE
